{
  "id": "newformattest2",
  "sources": [
    {
      "id": "0",
      "uri": "de.tudarmstadt.ukp.dkpro.core.api.lexmorph.type.pos.POS",
      "settings": {
        "categoriesWhitelist": ["NOUN", "ADV", "PRON", "ADP", "VERB"],
        "sourceFilesWhitelist": ["ID21200100.xmi"]
      },
      "createsGenerators": [
        {
          "type": "CategoryNumber",
          "name": "Gen1",
          "id": "POS_Numbers",
          "token": "CN",
          "settings": {},
          "extends": []
        },
        {
          "type": "TextFormatting",
          "name": "Gen2",
          "id": "POS_Formatting",
          "token": "TF",
          "extends": [],
          "settings": {
            "sofaFile": "ID21200100.xmi",
            "style": "underline"
          }
        }
      ]
    },
    {
      "id": "1",
      "uri": "de.tudarmstadt.ukp.dkpro.core.api.ner.type.NamedEntity",
      "settings": {
        "sourceFilesWhitelist": ["ID21200100.xmi"]
      },
      "createsGenerators": [
        {
          "type": "CategoryNumber",
          "name": "Gen3",
          "id": "NE_Numbers",
          "token": "CN",
          "settings": {},
          "extends": []
        },
        {
          "type": "TextFormatting",
          "name": "Gen4",
          "id": "NE_Formatting",
          "token": "TF",
          "extends": [],
          "settings": {
            "sofaFile": "ID21200100",
            "sofaID": "_InitialView",
            "style": "highlight"
          }
        }
      ]
    },
    {
      "id": "2",
      "uri": "",
      "createsGenerators": [
        {
          "id": "Total_Formatting",
          "name": "My DerivedGenerator",
          "type": "TextFormatting",
          "token": "TF",
          "settings": {},
          "extends": ["POS_Formatting", "NE_Formatting"]
        }
      ]
    }
  ],
  "widgets": [
    {
      "type": "StaticText",
      "title": "header",
      "src": "Parts of Speech and Named Entity",
      "options": {
        "style": "text-center fs-2 fw-bold fst-normal text-decoration-underline"
      },
      "icon": "bi bi-fonts",
      "w": 8,
      "h": 2,
      "x": 8,
      "y": 0,
      "id": "Text-3ujztrd"
    },
    {
      "type": "StaticImage",
      "title": "My Logo",
      "src": "https://placehold.co/600x400?text=My+Logo",
      "options": {},
      "icon": "bi bi-image",
      "w": 2,
      "h": 2,
      "x": 6,
      "y": 0,
      "id": "Image-zndq9sh"
    },
    {
      "type": "BarChart",
      "title": "Parts of Speech (POS)",
      "generator": {
        "id": "POS_Numbers"
      },
      "options": {
        "horizontal": false
      },
      "icon": "bi bi-bar-chart",
      "w": 8,
      "h": 6,
      "x": 0,
      "y": 4,
      "id": "bar-chart"
    },
    {
      "type": "HighlightText",
      "title": "POS & NE in one TextFormatting",
      "generator": {
        "id": "Total_Formatting"
      },
      "options": {},
      "icon": "bi bi-card-text",
      "w": 8,
      "h": 8,
      "x": 8,
      "y": 4,
      "id": "text"
    },
    {
      "type": "BarChart",
      "title": "Named Entities (NE)",
      "generator": {
        "id": "NE_Numbers"
      },
      "options": {
        "horizontal": true
      },
      "icon": "bi bi-bar-chart",
      "w": 8,
      "h": 6,
      "x": 16,
      "y": 4,
      "id": "bar-chart2"
    },
    {
      "type": "StaticText",
      "title": "Parts of Speech (POS) Caption",
      "src": "This is a caption to explain something important for the chart above.",
      "options": {
        "style": "text-end fs-6 fw-normal fst-italic text-decoration-none"
      },
      "icon": "bi bi-fonts",
      "w": 8,
      "h": 2,
      "x": 0,
      "y": 10,
      "id": "Text-lwq4zbo"
    },
    {
      "type": "StaticText",
      "title": "Named Entities (NE) Caption",
      "src": "This is a caption to explain something important for the chart above.",
      "options": {
        "style": "text-start fs-6 fw-normal fst-italic text-decoration-none"
      },
      "icon": "bi bi-fonts",
      "w": 8,
      "h": 2,
      "x": 16,
      "y": 10,
      "id": "Text-2smw5fr"
    }
  ]
}
